iot_manager_client/IoTClient.py
iot_manager_client/Packet.py
iot_manager_client/ReservedBytes.py
iot_manager_client/__init__.py
iot_manager_client/__main__.py
iot_manager_client-0.0.2.dist-info/METADATA
iot_manager_client-0.0.2.dist-info/WHEEL
iot_manager_client-0.0.2.dist-info/top_level.txt
iot_manager_client-0.0.2.dist-info/RECORD
